himena/__init__.py
himena/__main__.py
himena/_descriptors.py
himena/_drag.py
himena/_open_recent.py
himena/_socket.py
himena/_utils.py
himena/anchor.py
himena/app.py
himena/consts.py
himena/core.py
himena/exceptions.py
himena/io_utils.py
himena/layout.py
himena/profile.py
himena/types.py
himena/_app_model/__init__.py
himena/_app_model/_application.py
himena/_app_model/_command_registry.py
himena/_app_model/_context.py
himena/_app_model/_formatter.py
himena/_app_model/utils.py
himena/_app_model/actions/__init__.py
himena/_app_model/actions/_registry.py
himena/_app_model/actions/file_actions.py
himena/_app_model/actions/go_action.py
himena/_app_model/actions/help_actions.py
himena/_app_model/actions/tools_actions.py
himena/_app_model/actions/view_actions.py
himena/_app_model/actions/window_actions.py
himena/_cli/__init__.py
himena/_cli/install.py
himena/_cli/namespace.py
himena/_cli/profiles.py
himena/_providers/__init__.py
himena/_providers/core.py
himena/data_wrappers/__init__.py
himena/data_wrappers/_array.py
himena/data_wrappers/_dataframe.py
himena/data_wrappers/_tests/__init__.py
himena/data_wrappers/_tests/test_array_wrapper.py
himena/data_wrappers/_tests/test_dataframe_wrapper.py
himena/mock/__init__.py
himena/mock/main_window.py
himena/mock/widget.py
himena/plugins/__init__.py
himena/plugins/_checker.py
himena/plugins/_signature.py
himena/plugins/_utils.py
himena/plugins/actions.py
himena/plugins/config.py
himena/plugins/install.py
himena/plugins/io.py
himena/plugins/widget_class.py
himena/plugins/widget_plugins.py
himena/qt/__init__.py
himena/qt/_qclickable_label.py
himena/qt/_qcoloredit.py
himena/qt/_qcommand_palette.py
himena/qt/_qcontrolstack.py
himena/qt/_qdock_widget.py
himena/qt/_qdtypeedit.py
himena/qt/_qfinderwidget.py
himena/qt/_qflowchart.py
himena/qt/_qgoto.py
himena/qt/_qlineedit.py
himena/qt/_qmain_window.py
himena/qt/_qmodeldrop.py
himena/qt/_qnotification.py
himena/qt/_qparametric.py
himena/qt/_qprogress.py
himena/qt/_qrename.py
himena-0.1.7.dist-info/METADATA
himena-0.1.7.dist-info/WHEEL
himena-0.1.7.dist-info/entry_points.txt
himena-0.1.7.dist-info/licenses/LICENSE
himena-0.1.7.dist-info/RECORD
