Metadata-Version: 2.4
Name: himena
Version: 0.1.7
Summary: An infinitely extensible and reusable application framework.
Project-URL: Documentation, https://github.com/hanjinliu/himena#readme
Project-URL: Issues, https://github.com/hanjinliu/himena/issues
Project-URL: Source, https://github.com/hanjinliu/himena
Author-email: Hanjin Liu <liuhanjin.sc@gmail.com>
License: BSD 3-Clause License
License-File: LICENSE
Classifier: Development Status :: 4 - Beta
Classifier: Programming Language :: Python
Classifier: Programming Language :: Python :: 3.10
Classifier: Programming Language :: Python :: 3.11
Classifier: Programming Language :: Python :: 3.12
Classifier: Programming Language :: Python :: 3.13
Classifier: Programming Language :: Python :: 3.14
Classifier: Programming Language :: Python :: Implementation :: CPython
Classifier: Programming Language :: Python :: Implementation :: PyPy
Requires-Python: >=3.10
Requires-Dist: app-model>=0.4.0
Requires-Dist: chardet>=5.2.0
Requires-Dist: cmap>=0.4.0
Requires-Dist: magicgui>=0.10.0
Requires-Dist: numpy>=2.0.0
Requires-Dist: packaging>=24.0
Requires-Dist: pillow>=9.0.0
Requires-Dist: platformdirs>=4.3.6
Requires-Dist: pydantic>=2.10
Requires-Dist: pygments>=2.18.0
Requires-Dist: pyyaml>=6.0.1
Requires-Dist: qtpy>=2.3.1
Requires-Dist: superqt[iconify]>=0.7.3
Requires-Dist: tabulate>=0.9.0
Provides-Extra: all
Requires-Dist: ipython; extra == 'all'
Requires-Dist: matplotlib>=3.8.2; extra == 'all'
Requires-Dist: openpyxl; extra == 'all'
Requires-Dist: qtconsole; extra == 'all'
Requires-Dist: scipy; extra == 'all'
Provides-Extra: docs
Requires-Dist: griffe-fieldz; extra == 'docs'
Requires-Dist: ipython; extra == 'docs'
Requires-Dist: matplotlib>=3.8.2; extra == 'docs'
Requires-Dist: mkdocs; extra == 'docs'
Requires-Dist: mkdocs-autorefs; extra == 'docs'
Requires-Dist: mkdocs-gen-files; extra == 'docs'
Requires-Dist: mkdocs-material; extra == 'docs'
Requires-Dist: mkdocs-material-extensions; extra == 'docs'
Requires-Dist: mkdocstrings; extra == 'docs'
Requires-Dist: mkdocstrings-python; extra == 'docs'
Requires-Dist: openpyxl; extra == 'docs'
Requires-Dist: pyqt6; extra == 'docs'
Requires-Dist: qtconsole; extra == 'docs'
Requires-Dist: scipy; extra == 'docs'
Provides-Extra: pyqt5
Requires-Dist: pyqt5>=5.12.0; extra == 'pyqt5'
Provides-Extra: pyqt6
Requires-Dist: pyqt6; extra == 'pyqt6'
Provides-Extra: pyside6
Requires-Dist: pyside6; extra == 'pyside6'
Provides-Extra: recommended
Requires-Dist: ipython; extra == 'recommended'
Requires-Dist: matplotlib>=3.8.2; extra == 'recommended'
Requires-Dist: openpyxl; extra == 'recommended'
Requires-Dist: pyqt6; extra == 'recommended'
Requires-Dist: qtconsole; extra == 'recommended'
Requires-Dist: scipy; extra == 'recommended'
Provides-Extra: testing
Requires-Dist: click!=8.3.0; extra == 'testing'
Requires-Dist: dask; extra == 'testing'
Requires-Dist: ipython; extra == 'testing'
Requires-Dist: matplotlib>=3.8.2; extra == 'testing'
Requires-Dist: narwhals; extra == 'testing'
Requires-Dist: openpyxl; extra == 'testing'
Requires-Dist: pandas; extra == 'testing'
Requires-Dist: polars; extra == 'testing'
Requires-Dist: pyarrow; extra == 'testing'
Requires-Dist: pytest; extra == 'testing'
Requires-Dist: pytest-cov; extra == 'testing'
Requires-Dist: pytest-qt; extra == 'testing'
Requires-Dist: qtconsole; extra == 'testing'
Requires-Dist: scipy; extra == 'testing'
Requires-Dist: xarray; extra == 'testing'
Requires-Dist: zarr; extra == 'testing'
